setup.cfg
setup.py
src/ubjsonstream/__init__.py
src/ubjsonstream/reader.py
src/ubjsonstream/writer.py
src/ubjsonstream.egg-info/PKG-INFO
src/ubjsonstream.egg-info/SOURCES.txt
src/ubjsonstream.egg-info/dependency_links.txt
src/ubjsonstream.egg-info/requires.txt
src/ubjsonstream.egg-info/top_level.txt