Metadata-Version: 1.1
Name: ubjsonstream
Version: 0.0.2
Summary: A library for serializing and async deserializing UBJSON
Home-page: UNKNOWN
Author: Tomasz Sieprawski
Author-email: tomasz@sieprawski.eu
License: MIT
Keywords: ubjson
Platform: UNKNOWN
Classifier: Development Status :: 3 - Alpha
Classifier: Intended Audience :: Developers
Classifier: Topic :: Software Development :: Build Tools
Classifier: License :: OSI Approved :: MIT License
Classifier: Programming Language :: Python :: 3
